plex/__init__.py
plex/actions.py
plex/dfa.py
plex/errors.py
plex/lexicons.py
plex/machines.py
plex/regexps.py
plex/scanners.py
plex/timing.py
plex/traditional.py
plex/transitions.py
plex/__pycache__/__init__.cpython-36.pyc
plex/__pycache__/actions.cpython-36.pyc
plex/__pycache__/dfa.cpython-36.pyc
plex/__pycache__/errors.cpython-36.pyc
plex/__pycache__/lexicons.cpython-36.pyc
plex/__pycache__/machines.cpython-36.pyc
plex/__pycache__/regexps.cpython-36.pyc
plex/__pycache__/scanners.cpython-36.pyc
plex/__pycache__/traditional.cpython-36.pyc
plex/__pycache__/transitions.cpython-36.pyc
plex.egg-info/PKG-INFO
plex.egg-info/SOURCES.txt
plex.egg-info/dependency_links.txt
plex.egg-info/entry_points.txt
plex.egg-info/not-zip-safe
plex.egg-info/requires.txt
plex.egg-info/top_level.txt
plex3-2.0.0.dev0.dist-info/DESCRIPTION.rst
plex3-2.0.0.dev0.dist-info/METADATA
plex3-2.0.0.dev0.dist-info/RECORD
plex3-2.0.0.dev0.dist-info/WHEEL
plex3-2.0.0.dev0.dist-info/entry_points.txt
plex3-2.0.0.dev0.dist-info/metadata.json
plex3-2.0.0.dev0.dist-info/top_level.txt
