Metadata-Version: 2.0
Name: plex3
Version: 2.0.0.dev0
Summary: Plex is a library building lexical analysers
Home-page: http://www.cosc.canterbury.ac.nz/greg.ewing/python/Plex/
Author: Stephane Klein
Author-email: stephane@harobed.org
License: LGPL
Platform: UNKNOWN
Requires-Dist: nose
Requires-Dist: sphinx
Requires-Dist: six
